adirondax/__init__.py
adirondax/constants.py
adirondax/defaults.json
adirondax/gravity.py
adirondax/quantum.py
adirondax/simulation.py
adirondax/utils.py
adirondax/visualization.py
adirondax/hydro/__init__.py
adirondax/hydro/common2d.py
adirondax/hydro/euler2d.py
adirondax/hydro/mhd2d.py
adirondax-0.0.4.dist-info/licenses/LICENSE
adirondax-0.0.4.dist-info/METADATA
adirondax-0.0.4.dist-info/WHEEL
adirondax-0.0.4.dist-info/top_level.txt
adirondax-0.0.4.dist-info/RECORD
