Metadata-Version: 2.4
Name: adirondax
Version: 0.0.4
Summary: A differentiable astrophysics simulator in JAX
Author-email: Philip Mocz <philip.mocz@gmail.com>
License-Expression: Apache-2.0
Project-URL: Documentation, https://adirondax.readthedocs.io
Project-URL: Homepage, https://github.com/AdirondaxProject/adirondax
Requires-Python: >=3.11
License-File: LICENSE
Requires-Dist: jax==0.8.0
Requires-Dist: jaxdecomp==0.2.9
Requires-Dist: tensorflow
Requires-Dist: orbax-checkpoint==0.11.28
Requires-Dist: optax==0.2.6
Requires-Dist: jaxopt
Requires-Dist: numpy
Requires-Dist: matplotlib
Requires-Dist: setuptools>=70.1.1
Provides-Extra: cuda12
Requires-Dist: jax[cuda12]==0.5.3; extra == "cuda12"
Dynamic: license-file
